README.rst
dirwatch.py
setup.py
dirwatch.egg-info/PKG-INFO
dirwatch.egg-info/SOURCES.txt
dirwatch.egg-info/dependency_links.txt
dirwatch.egg-info/top_level.txt