Metadata-Version: 1.0
Name: dirwatch
Version: 1.0
Summary: Simple cross-platform file changes watcher
Home-page: http://github.com/pistolero/dirwatch
Author: Sergey Kirillov
Author-email: sergey.kirillov@gmail.com
License: UNKNOWN
Platform: UNKNOWN
